GoldenSectionSearch/GoldenSectionSearch.py
GoldenSectionSearch/__init__.py
GoldenSectionSearch-0.0.6.dist-info/METADATA
GoldenSectionSearch-0.0.6.dist-info/WHEEL
GoldenSectionSearch-0.0.6.dist-info/top_level.txt
GoldenSectionSearch-0.0.6.dist-info/RECORD
