Metadata-Version: 2.1
Name: GoldenSectionSearch
Version: 0.0.6
Summary: This package is to print and plot Golden Section Algorithm
Home-page: UNKNOWN
Author: Vishal Pandey
Author-email: vishalp316253@gmail.com
License: UNKNOWN
Platform: UNKNOWN
Classifier: Programming Language :: Python :: 3
Classifier: License :: OSI Approved :: MIT License
Classifier: Natural Language :: English
Classifier: Operating System :: OS Independent
Requires-Python: >=3.0
Requires-Dist: numpy
Requires-Dist: matplotlib
Requires-Dist: IPython
Requires-Dist: time
